{
  "saved_at": "2026-03-26T11:08:14.351080",
  "date": "2026-03-26",
  "time": "11:08",
  "sgp_proposals": [
    {
      "match": "Pittsburgh (Penguins) @ Ottawa (Senateurs)",
      "short_match": "Penguins @ Senateurs",
      "combo_type": "Gagnant + Total de buts",
      "label": "Victoire Penguins + Moins de 3.5",
      "combined_odds": 4.07,
      "avg_score": 90.5,
      "mise": null,
      "picks": [
        {
          "bet_type": "Gagnant à 2 issues",
          "selection": "Pittsburgh (Penguins)",
          "odds": 2.3,
          "fair_prob": 50.8,
          "value_score": 96.6
        },
        {
          "bet_type": "Ottawa (Sénateurs) Total de buts plus/moins 3.5",
          "selection": "Moins de 3.5",
          "odds": 1.77,
          "fair_prob": 53.1,
          "value_score": 84.5
        }
      ]
    },
    {
      "match": "New Jersey (Devils) @ Nashville (Predators)",
      "short_match": "Devils @ Predators",
      "combo_type": "Gagnant + Total de buts",
      "label": "Victoire Devils + Moins de 3.5",
      "combined_odds": 3.23,
      "avg_score": 90.5,
      "mise": null,
      "picks": [
        {
          "bet_type": "Gagnant à 2 issues",
          "selection": "New Jersey (Devils)",
          "odds": 1.98,
          "fair_prob": 49.2,
          "value_score": 96.6
        },
        {
          "bet_type": "Nashville (Predators) Total de buts plus/moins 3.5",
          "selection": "Moins de 3.5",
          "odds": 1.63,
          "fair_prob": 58,
          "value_score": 84.5
        }
      ]
    },
    {
      "match": "Chicago (Blackhawks) @ Philadelphie (Flyers)",
      "short_match": "Blackhawks @ Flyers",
      "combo_type": "Gagnant + Total de buts",
      "label": "Victoire Flyers + Moins de 3.5",
      "combined_odds": 2.64,
      "avg_score": 90.5,
      "mise": null,
      "picks": [
        {
          "bet_type": "Gagnant à 2 issues",
          "selection": "Philadelphie (Flyers)",
          "odds": 1.6,
          "fair_prob": 56.1,
          "value_score": 96.6
        },
        {
          "bet_type": "Philadelphie (Flyers) Total de buts plus/moins 3.5",
          "selection": "Moins de 3.5",
          "odds": 1.65,
          "fair_prob": 57.1,
          "value_score": 84.5
        }
      ]
    }
  ],
  "picks": [
    {
      "key": "",
      "match": "Pittsburgh (Penguins) @ Ottawa (Senateurs)",
      "home_team": "",
      "away_team": "",
      "selection": "Pittsburgh (Penguins)",
      "bet_type": "Gagnant à 2 issues",
      "odds": 2.3,
      "fair_prob": 50.8,
      "value_score": 96.6,
      "mise": 3.5,
      "recommendation": "Excellent ***",
      "champion": true
    },
    {
      "key": "",
      "match": "Columbus (Blue Jackets) @ Montreal (Canadiens)",
      "home_team": "",
      "away_team": "",
      "selection": "Columbus (Blue Jackets)",
      "bet_type": "Gagnant à 2 issues",
      "odds": 2.05,
      "fair_prob": 48.8,
      "value_score": 96.6,
      "mise": 0.5,
      "recommendation": "Excellent ***",
      "champion": true
    },
    {
      "key": "",
      "match": "New Jersey (Devils) @ Nashville (Predators)",
      "home_team": "",
      "away_team": "",
      "selection": "New Jersey (Devils)",
      "bet_type": "Gagnant à 2 issues",
      "odds": 1.98,
      "fair_prob": 49.2,
      "value_score": 96.6,
      "mise": null,
      "recommendation": "Excellent ***",
      "champion": true
    },
    {
      "key": "",
      "match": "Seattle (Kraken) @ Tampa Bay (Lightning)",
      "home_team": "",
      "away_team": "",
      "selection": "Tampa Bay (Lightning)",
      "bet_type": "Gagnant à 2 issues",
      "odds": 1.36,
      "fair_prob": 71.6,
      "value_score": 81.3,
      "mise": null,
      "recommendation": "Excellent ***",
      "champion": true
    },
    {
      "key": "",
      "match": "Columbus (Blue Jackets) @ Montreal (Canadiens)",
      "home_team": "",
      "away_team": "",
      "selection": "Plus de 6.5",
      "bet_type": "Total de buts plus/moins 6.5",
      "odds": 1.91,
      "fair_prob": 50.5,
      "value_score": 81,
      "mise": null,
      "recommendation": "Excellent ***",
      "champion": true
    },
    {
      "key": "",
      "match": "New Jersey (Devils) @ Nashville (Predators)",
      "home_team": "",
      "away_team": "",
      "selection": "Moins de 3.5",
      "bet_type": "Nashville (Predators) Total de buts plus/moins 3.5",
      "odds": 1.63,
      "fair_prob": 58,
      "value_score": 84.5,
      "mise": null,
      "recommendation": "Excellent ***",
      "champion": false
    },
    {
      "key": "",
      "match": "Chicago (Blackhawks) @ Philadelphie (Flyers)",
      "home_team": "",
      "away_team": "",
      "selection": "Moins de 3.5",
      "bet_type": "Philadelphie (Flyers) Total de buts plus/moins 3.5",
      "odds": 1.65,
      "fair_prob": 57.1,
      "value_score": 84.5,
      "mise": null,
      "recommendation": "Excellent ***",
      "champion": false
    },
    {
      "key": "",
      "match": "Seattle (Kraken) @ Tampa Bay (Lightning)",
      "home_team": "",
      "away_team": "",
      "selection": "Plus de 3.5",
      "bet_type": "Tampa Bay (Lightning) Total de buts plus/moins 3.5",
      "odds": 1.67,
      "fair_prob": 56.3,
      "value_score": 84.5,
      "mise": null,
      "recommendation": "Excellent ***",
      "champion": false
    },
    {
      "key": "",
      "match": "Edmonton (Oilers) @ Vegas (Golden Knights)",
      "home_team": "",
      "away_team": "",
      "selection": "Vegas (Golden Knights)",
      "bet_type": "Gagnant à 2 issues",
      "odds": 1.76,
      "fair_prob": 62.3,
      "value_score": 96.6,
      "mise": 4,
      "recommendation": "Excellent ***",
      "champion": false
    },
    {
      "key": "",
      "match": "Minnesota (Wild) @ Floride (Panthers)",
      "home_team": "",
      "away_team": "",
      "selection": "Minnesota (Wild)",
      "bet_type": "Gagnant à 2 issues",
      "odds": 1.66,
      "fair_prob": 62,
      "value_score": 96.6,
      "mise": 1.5,
      "recommendation": "Excellent ***",
      "champion": false
    },
    {
      "key": "",
      "match": "Colorado (Avalanche) @ Winnipeg (Jets)",
      "home_team": "",
      "away_team": "",
      "selection": "Colorado (Avalanche)",
      "bet_type": "Gagnant à 2 issues",
      "odds": 1.54,
      "fair_prob": 61.4,
      "value_score": 96.6,
      "mise": null,
      "recommendation": "Excellent ***",
      "champion": false
    },
    {
      "key": "",
      "match": "Dallas (Stars) @ New York (Islanders)",
      "home_team": "",
      "away_team": "",
      "selection": "Plus de 2.5",
      "bet_type": "New York (Islanders) Total de buts plus/moins 2.5",
      "odds": 1.71,
      "fair_prob": 54.5,
      "value_score": 84.5,
      "mise": null,
      "recommendation": "Excellent ***",
      "champion": false
    },
    {
      "key": "",
      "match": "Los Angeles (Kings) @ Vancouver (Canucks)",
      "home_team": "",
      "away_team": "",
      "selection": "Los Angeles (Kings)",
      "bet_type": "Gagnant à 2 issues",
      "odds": 1.58,
      "fair_prob": 60.3,
      "value_score": 96.6,
      "mise": null,
      "recommendation": "Excellent ***",
      "champion": false
    },
    {
      "key": "",
      "match": "Minnesota (Wild) @ Floride (Panthers)",
      "home_team": "",
      "away_team": "",
      "selection": "Plus de 2.5",
      "bet_type": "Floride (Panthers) Total de buts plus/moins 2.5",
      "odds": 1.73,
      "fair_prob": 54.2,
      "value_score": 84.5,
      "mise": null,
      "recommendation": "Excellent ***",
      "champion": false
    },
    {
      "key": "",
      "match": "Washington (Capitals) @ Utah (Mammoth)",
      "home_team": "",
      "away_team": "",
      "selection": "Moins de 3.5",
      "bet_type": "Utah (Mammoth) Total de buts plus/moins 3.5",
      "odds": 1.73,
      "fair_prob": 54.2,
      "value_score": 84.5,
      "mise": null,
      "recommendation": "Excellent ***",
      "champion": false
    },
    {
      "key": "",
      "match": "San Jose (Sharks) @ Saint-Louis (Blues)",
      "home_team": "",
      "away_team": "",
      "selection": "Saint-Louis (Blues)",
      "bet_type": "Gagnant à 2 issues",
      "odds": 1.7,
      "fair_prob": 59.5,
      "value_score": 96.6,
      "mise": 0.5,
      "recommendation": "Excellent ***",
      "champion": false
    },
    {
      "key": "",
      "match": "San Jose (Sharks) @ Saint-Louis (Blues)",
      "home_team": "",
      "away_team": "",
      "selection": "Moins de 3.5",
      "bet_type": "Saint-Louis (Blues) Total de buts plus/moins 3.5",
      "odds": 1.77,
      "fair_prob": 53.1,
      "value_score": 84.5,
      "mise": null,
      "recommendation": "Excellent ***",
      "champion": false
    },
    {
      "key": "",
      "match": "Los Angeles (Kings) @ Vancouver (Canucks)",
      "home_team": "",
      "away_team": "",
      "selection": "Moins de 3.5",
      "bet_type": "Los Angeles (Kings) Total de buts plus/moins 3.5",
      "odds": 1.77,
      "fair_prob": 53.1,
      "value_score": 84.5,
      "mise": null,
      "recommendation": "Excellent ***",
      "champion": false
    },
    {
      "key": "",
      "match": "Pittsburgh (Penguins) @ Ottawa (Senateurs)",
      "home_team": "",
      "away_team": "",
      "selection": "Moins de 3.5",
      "bet_type": "Ottawa (Sénateurs) Total de buts plus/moins 3.5",
      "odds": 1.77,
      "fair_prob": 53.1,
      "value_score": 84.5,
      "mise": null,
      "recommendation": "Excellent ***",
      "champion": false
    },
    {
      "key": "",
      "match": "Anaheim (Ducks) @ Calgary (Flames)",
      "home_team": "",
      "away_team": "",
      "selection": "Moins de 3.5",
      "bet_type": "Anaheim (Ducks) Total de buts plus/moins 3.5",
      "odds": 1.78,
      "fair_prob": 52.7,
      "value_score": 84.5,
      "mise": null,
      "recommendation": "Excellent ***",
      "champion": false
    },
    {
      "key": "",
      "match": "Chicago (Blackhawks) @ Philadelphie (Flyers)",
      "home_team": "",
      "away_team": "",
      "selection": "Philadelphie (Flyers)",
      "bet_type": "Gagnant à 2 issues",
      "odds": 1.6,
      "fair_prob": 56.1,
      "value_score": 96.6,
      "mise": null,
      "recommendation": "Excellent ***",
      "champion": false
    },
    {
      "key": "",
      "match": "Dallas (Stars) @ New York (Islanders)",
      "home_team": "",
      "away_team": "",
      "selection": "Dallas (Stars)",
      "bet_type": "Gagnant à 2 issues",
      "odds": 1.78,
      "fair_prob": 54.9,
      "value_score": 96.6,
      "mise": null,
      "recommendation": "Excellent ***",
      "champion": false
    },
    {
      "key": "",
      "match": "Anaheim (Ducks) @ Calgary (Flames)",
      "home_team": "",
      "away_team": "",
      "selection": "Anaheim (Ducks)",
      "bet_type": "Gagnant à 2 issues",
      "odds": 1.72,
      "fair_prob": 54.1,
      "value_score": 96.6,
      "mise": null,
      "recommendation": "Excellent ***",
      "champion": false
    },
    {
      "key": "",
      "match": "Washington (Capitals) @ Utah (Mammoth)",
      "home_team": "",
      "away_team": "",
      "selection": "Utah (Mammoth)",
      "bet_type": "Gagnant à 2 issues",
      "odds": 1.66,
      "fair_prob": 53.6,
      "value_score": 96.6,
      "mise": null,
      "recommendation": "Excellent ***",
      "champion": false
    },
    {
      "key": "",
      "match": "Edmonton (Oilers) @ Vegas (Golden Knights)",
      "home_team": "",
      "away_team": "",
      "selection": "Plus de 0.5",
      "bet_type": "Pavel Dorofeyev Total de points 0.5",
      "odds": 1.67,
      "fair_prob": 56.3,
      "value_score": 64,
      "mise": null,
      "recommendation": "Excellent ***",
      "champion": false
    },
    {
      "key": "",
      "match": "Colorado (Avalanche) @ Winnipeg (Jets)",
      "home_team": "",
      "away_team": "",
      "selection": "Moins de 6.5",
      "bet_type": "Total de buts plus/moins 6.5",
      "odds": 1.77,
      "fair_prob": 54.8,
      "value_score": 81,
      "mise": null,
      "recommendation": "Excellent ***",
      "champion": false
    },
    {
      "key": "",
      "match": "Dallas (Stars) @ New York (Islanders)",
      "home_team": "",
      "away_team": "",
      "selection": "Nul ou Dallas (Stars)",
      "bet_type": "Double chance",
      "odds": 1.5,
      "fair_prob": 31.6,
      "value_score": 40,
      "mise": null,
      "recommendation": "Neutre *",
      "champion": false
    },
    {
      "key": "",
      "match": "Columbus (Blue Jackets) @ Montreal (Canadiens)",
      "home_team": "",
      "away_team": "",
      "selection": "Montreal (Canadiens) ou Nul",
      "bet_type": "Double chance",
      "odds": 1.5,
      "fair_prob": 31.5,
      "value_score": 40,
      "mise": null,
      "recommendation": "Neutre *",
      "champion": false
    },
    {
      "key": "",
      "match": "New Jersey (Devils) @ Nashville (Predators)",
      "home_team": "",
      "away_team": "",
      "selection": "Nashville (Predators) ou Nul",
      "bet_type": "Double chance",
      "odds": 1.53,
      "fair_prob": 31,
      "value_score": 40,
      "mise": null,
      "recommendation": "Neutre *",
      "champion": false
    },
    {
      "key": "",
      "match": "Edmonton (Oilers) @ Vegas (Golden Knights)",
      "home_team": "",
      "away_team": "",
      "selection": "Nul ou Edmonton (Oilers)",
      "bet_type": "Double chance",
      "odds": 1.67,
      "fair_prob": 28.3,
      "value_score": 40,
      "mise": null,
      "recommendation": "Neutre *",
      "champion": false
    },
    {
      "key": "",
      "match": "San Jose (Sharks) @ Saint-Louis (Blues)",
      "home_team": "",
      "away_team": "",
      "selection": "Nul ou San Jose (Sharks)",
      "bet_type": "Double chance",
      "odds": 1.73,
      "fair_prob": 27.4,
      "value_score": 40,
      "mise": null,
      "recommendation": "Neutre *",
      "champion": false
    },
    {
      "key": "",
      "match": "Anaheim (Ducks) @ Calgary (Flames)",
      "home_team": "",
      "away_team": "",
      "selection": "Calgary (Flames) ou Nul",
      "bet_type": "Double chance",
      "odds": 1.73,
      "fair_prob": 27.4,
      "value_score": 40,
      "mise": null,
      "recommendation": "Neutre *",
      "champion": false
    },
    {
      "key": "",
      "match": "Washington (Capitals) @ Utah (Mammoth)",
      "home_team": "",
      "away_team": "",
      "selection": "Nul ou Washington (Capitals)",
      "bet_type": "Double chance",
      "odds": 1.73,
      "fair_prob": 27.4,
      "value_score": 40,
      "mise": null,
      "recommendation": "Neutre *",
      "champion": false
    },
    {
      "key": "",
      "match": "Pittsburgh (Penguins) @ Ottawa (Senateurs)",
      "home_team": "",
      "away_team": "",
      "selection": "Nul ou Pittsburgh (Penguins)",
      "bet_type": "Double chance",
      "odds": 1.73,
      "fair_prob": 27.4,
      "value_score": 40,
      "mise": null,
      "recommendation": "Neutre *",
      "champion": false
    },
    {
      "key": "",
      "match": "Minnesota (Wild) @ Floride (Panthers)",
      "home_team": "",
      "away_team": "",
      "selection": "Floride (Panthers) ou Nul",
      "bet_type": "Double chance",
      "odds": 1.8,
      "fair_prob": 26.3,
      "value_score": 40,
      "mise": null,
      "recommendation": "Neutre *",
      "champion": false
    },
    {
      "key": "",
      "match": "Chicago (Blackhawks) @ Philadelphie (Flyers)",
      "home_team": "",
      "away_team": "",
      "selection": "Nul ou Chicago (Blackhawks)",
      "bet_type": "Double chance",
      "odds": 1.83,
      "fair_prob": 25.8,
      "value_score": 40,
      "mise": null,
      "recommendation": "Neutre *",
      "champion": false
    }
  ]
}