{"DET|TBL": {"winner": "home", "home_score": 4, "away_score": 3, "state": "OFF", "home_name": "Lightning", "away_name": "Red Wings", "home_abbrev": "TBL", "away_abbrev": "DET", "start_time_utc": "2026-04-13T23:00:00Z", "period": 4, "period_type": "OT", "time_remaining": "04:33", "in_intermission": false}, "red wings|lightning": {"winner": "home", "home_score": 4, "away_score": 3, "state": "OFF", "home_name": "Lightning", "away_name": "Red Wings", "home_abbrev": "TBL", "away_abbrev": "DET", "start_time_utc": "2026-04-13T23:00:00Z", "period": 4, "period_type": "OT", "time_remaining": "04:33", "in_intermission": false}, "NYR|FLA": {"winner": "home", "home_score": 3, "away_score": 2, "state": "OFF", "home_name": "Panthers", "away_name": "Rangers", "home_abbrev": "FLA", "away_abbrev": "NYR", "start_time_utc": "2026-04-13T23:00:00Z", "period": 3, "period_type": "REG", "time_remaining": "00:00", "in_intermission": false}, "rangers|panthers": {"winner": "home", "home_score": 3, "away_score": 2, "state": "OFF", "home_name": "Panthers", "away_name": "Rangers", "home_abbrev": "FLA", "away_abbrev": "NYR", "start_time_utc": "2026-04-13T23:00:00Z", "period": 3, "period_type": "REG", "time_remaining": "00:00", "in_intermission": false}, "CAR|PHI": {"winner": "home", "home_score": 3, "away_score": 2, "state": "OFF", "home_name": "Flyers", "away_name": "Hurricanes", "home_abbrev": "PHI", "away_abbrev": "CAR", "start_time_utc": "2026-04-13T23:00:00Z", "period": 5, "period_type": "SO", "time_remaining": "00:00", "in_intermission": false}, "hurricanes|flyers": {"winner": "home", "home_score": 3, "away_score": 2, "state": "OFF", "home_name": "Flyers", "away_name": "Hurricanes", "home_abbrev": "PHI", "away_abbrev": "CAR", "start_time_utc": "2026-04-13T23:00:00Z", "period": 5, "period_type": "SO", "time_remaining": "00:00", "in_intermission": false}, "DAL|TOR": {"winner": "away", "home_score": 5, "away_score": 6, "state": "OFF", "home_name": "Maple Leafs", "away_name": "Stars", "home_abbrev": "TOR", "away_abbrev": "DAL", "start_time_utc": "2026-04-13T23:30:00Z", "period": 3, "period_type": "REG", "time_remaining": "00:00", "in_intermission": false}, "stars|maple leafs": {"winner": "away", "home_score": 5, "away_score": 6, "state": "OFF", "home_name": "Maple Leafs", "away_name": "Stars", "home_abbrev": "TOR", "away_abbrev": "DAL", "start_time_utc": "2026-04-13T23:30:00Z", "period": 3, "period_type": "REG", "time_remaining": "00:00", "in_intermission": false}, "MIN|STL": {"winner": "home", "home_score": 6, "away_score": 3, "state": "OFF", "home_name": "Blues", "away_name": "Wild", "home_abbrev": "STL", "away_abbrev": "MIN", "start_time_utc": "2026-04-14T00:00:00Z", "period": 3, "period_type": "REG", "time_remaining": "00:00", "in_intermission": false}, "wild|blues": {"winner": "home", "home_score": 6, "away_score": 3, "state": "OFF", "home_name": "Blues", "away_name": "Wild", "home_abbrev": "STL", "away_abbrev": "MIN", "start_time_utc": "2026-04-14T00:00:00Z", "period": 3, "period_type": "REG", "time_remaining": "00:00", "in_intermission": false}, "SJS|NSH": {"winner": "away", "home_score": 2, "away_score": 3, "state": "OFF", "home_name": "Predators", "away_name": "Sharks", "home_abbrev": "NSH", "away_abbrev": "SJS", "start_time_utc": "2026-04-14T00:00:00Z", "period": 3, "period_type": "REG", "time_remaining": "00:00", "in_intermission": false}, "sharks|predators": {"winner": "away", "home_score": 2, "away_score": 3, "state": "OFF", "home_name": "Predators", "away_name": "Sharks", "home_abbrev": "NSH", "away_abbrev": "SJS", "start_time_utc": "2026-04-14T00:00:00Z", "period": 3, "period_type": "REG", "time_remaining": "00:00", "in_intermission": false}, "BUF|CHI": {"winner": "away", "home_score": 1, "away_score": 5, "state": "OFF", "home_name": "Blackhawks", "away_name": "Sabres", "home_abbrev": "CHI", "away_abbrev": "BUF", "start_time_utc": "2026-04-14T00:30:00Z", "period": 3, "period_type": "REG", "time_remaining": "00:00", "in_intermission": false}, "sabres|blackhawks": {"winner": "away", "home_score": 1, "away_score": 5, "state": "OFF", "home_name": "Blackhawks", "away_name": "Sabres", "home_abbrev": "CHI", "away_abbrev": "BUF", "start_time_utc": "2026-04-14T00:30:00Z", "period": 3, "period_type": "REG", "time_remaining": "00:00", "in_intermission": false}, "COL|EDM": {"winner": "away", "home_score": 1, "away_score": 2, "state": "OFF", "home_name": "Oilers", "away_name": "Avalanche", "home_abbrev": "EDM", "away_abbrev": "COL", "start_time_utc": "2026-04-14T01:30:00Z", "period": 5, "period_type": "SO", "time_remaining": "00:00", "in_intermission": false}, "avalanche|oilers": {"winner": "away", "home_score": 1, "away_score": 2, "state": "OFF", "home_name": "Oilers", "away_name": "Avalanche", "home_abbrev": "EDM", "away_abbrev": "COL", "start_time_utc": "2026-04-14T01:30:00Z", "period": 5, "period_type": "SO", "time_remaining": "00:00", "in_intermission": false}, "LAK|SEA": {"winner": "away", "home_score": 3, "away_score": 5, "state": "OFF", "home_name": "Kraken", "away_name": "Kings", "home_abbrev": "SEA", "away_abbrev": "LAK", "start_time_utc": "2026-04-14T01:30:00Z", "period": 3, "period_type": "REG", "time_remaining": "00:00", "in_intermission": false}, "kings|kraken": {"winner": "away", "home_score": 3, "away_score": 5, "state": "OFF", "home_name": "Kraken", "away_name": "Kings", "home_abbrev": "SEA", "away_abbrev": "LAK", "start_time_utc": "2026-04-14T01:30:00Z", "period": 3, "period_type": "REG", "time_remaining": "00:00", "in_intermission": false}, "WPG|VGK": {"winner": "home", "home_score": 6, "away_score": 2, "state": "OFF", "home_name": "Golden Knights", "away_name": "Jets", "home_abbrev": "VGK", "away_abbrev": "WPG", "start_time_utc": "2026-04-14T02:00:00Z", "period": 3, "period_type": "REG", "time_remaining": "00:00", "in_intermission": false}, "jets|golden knights": {"winner": "home", "home_score": 6, "away_score": 2, "state": "OFF", "home_name": "Golden Knights", "away_name": "Jets", "home_abbrev": "VGK", "away_abbrev": "WPG", "start_time_utc": "2026-04-14T02:00:00Z", "period": 3, "period_type": "REG", "time_remaining": "00:00", "in_intermission": false}}